MANIFEST.in
Makefile.in
README.md
config.guess
config.mk.in
config.sub
configure
install-sh
pyproject.toml
setup.py
bin/amuse-tutorial
bin/amusifier.in
lib/amuse_mpi/Makefile
lib/amuse_mpi/amuse_mpi.c
lib/amuse_mpi/amuse_mpi.h
lib/forsockets/Makefile
lib/forsockets/forsockets.c
lib/forsockets/forsockets.h
lib/forsockets/forsocketsf.f90
lib/g6/Makefile
lib/g6/g6lib.c
lib/g6/g6lib.h
lib/sapporo_2/Makefile
lib/sapporo_2/download.py
lib/sapporo_light/Makefile
lib/sapporo_light/README
lib/sapporo_light/dev_evaluate_gravity.cu
lib/sapporo_light/g6lib.c
lib/sapporo_light/g6lib.h
lib/sapporo_light/host_evaluate_gravity.cu
lib/sapporo_light/sapporo.cpp
lib/sapporo_light/sapporo.h
lib/sapporo_light/sapporoG6lib.cpp
lib/sapporo_light/sapporo_defs.h
lib/sapporo_light/sapporo_multi.h
lib/sapporo_light/send_fetch_data.cpp
lib/simple_hash/Makefile
lib/simple_hash/simple_hash.c
lib/simple_hash/simple_hash.h
lib/simple_hash/test.cpp
lib/simple_hash/test.py
lib/stopcond/Makefile
lib/stopcond/stopcond.c
lib/stopcond/stopcond.h
lib/stopcond/stopcond.inc
lib/stopcond/stopcondf.F90
lib/stopcond/stopcondf_isoc.F90
lib/stopcond/mpi/Makefile
src/amuse/__init__.py
src/amuse/_version.py
src/amuse/amuserc
src/amuse/codes.py
src/amuse/config.py
src/amuse/lab.py
src/amuse/community/__init__.py
src/amuse/community/interface/__init__.py
src/amuse/community/interface/common.py
src/amuse/community/interface/example.py
src/amuse/community/interface/gd.py
src/amuse/community/interface/hydro.py
src/amuse/community/interface/mhd.py
src/amuse/community/interface/se.py
src/amuse/community/interface/stopping_conditions.py
src/amuse/couple/__init__.py
src/amuse/couple/bridge.py
src/amuse/couple/collision_handler.py
src/amuse/couple/encounters.py
src/amuse/couple/fallback_stellar_evolution.py
src/amuse/couple/multiples.py
src/amuse/couple/parallel_stellar_evolution.py
src/amuse/data/AMUSE.bib
src/amuse/data/__init__.py
src/amuse/datamodel/__init__.py
src/amuse/datamodel/attributes.py
src/amuse_framework.egg-info/PKG-INFO
src/amuse_framework.egg-info/SOURCES.txt
src/amuse_framework.egg-info/dependency_links.txt
src/amuse_framework.egg-info/requires.txt
src/amuse_framework.egg-info/top_level.txt
