Metadata-Version: 2.1
Name: amuse-framework
Version: 2024.4.0
Summary: The Astrophysical Multipurpose Software Environment
Home-page: http://www.amusecode.org/
Author: The AMUSE team
Author-email: info@amusecode.org
License: Apache License 2.0
Classifier: Development Status :: 5 - Production/Stable
Classifier: Environment :: Console
Classifier: Intended Audience :: End Users/Desktop
Classifier: Intended Audience :: Developers
Classifier: Intended Audience :: Science/Research
Classifier: License :: OSI Approved :: Apache Software License
Classifier: Operating System :: MacOS :: MacOS X
Classifier: Operating System :: POSIX
Classifier: Programming Language :: Python :: 3
Classifier: Programming Language :: Python :: 3.6
Classifier: Programming Language :: Python :: 3.7
Classifier: Programming Language :: Python :: 3.8
Classifier: Programming Language :: Python :: 3.9
Classifier: Programming Language :: C
Classifier: Programming Language :: C++
Classifier: Programming Language :: Fortran
Classifier: Topic :: Scientific/Engineering :: Astronomy
Requires-Python: >=3.7
Requires-Dist: setuptools>=41.0.0
Requires-Dist: setuptools_scm
Requires-Dist: pip>=19.0.0
Requires-Dist: wheel>=0.32
Requires-Dist: docutils>=0.6
Requires-Dist: numpy>=1.2.2
Requires-Dist: pytest>=4.0
Requires-Dist: h5py>=1.1.0
Provides-Extra: mpi
Requires-Dist: mpi4py>=1.1.0; extra == "mpi"
